{"nodes": [{"id": "e_prophunt_crm_backend_middlewares_auth_js", "label": "auth.js", "file_type": "code", "source_file": "E:\\PROPHUNT CRM\\backend\\middlewares\\auth.js", "source_location": "L1"}, {"id": "middlewares_auth_jwt", "label": "jwt", "file_type": "code", "source_file": "E:\\PROPHUNT CRM\\backend\\middlewares\\auth.js", "source_location": "L2"}, {"id": "middlewares_auth_user", "label": "User", "file_type": "code", "source_file": "E:\\PROPHUNT CRM\\backend\\middlewares\\auth.js", "source_location": "L3"}, {"id": "middlewares_auth_organization", "label": "Organization", "file_type": "code", "source_file": "E:\\PROPHUNT CRM\\backend\\middlewares\\auth.js", "source_location": "L4"}, {"id": "middlewares_auth_apperror", "label": "{ AppError }", "file_type": "code", "source_file": "E:\\PROPHUNT CRM\\backend\\middlewares\\auth.js", "source_location": "L5"}, {"id": "middlewares_auth_orgcache", "label": "_orgCache", "file_type": "code", "source_file": "E:\\PROPHUNT CRM\\backend\\middlewares\\auth.js", "source_location": "L10"}, {"id": "middlewares_auth_getcachedorg", "label": "_getCachedOrg()", "file_type": "code", "source_file": "E:\\PROPHUNT CRM\\backend\\middlewares\\auth.js", "source_location": "L13"}, {"id": "middlewares_auth_setcachedorg", "label": "_setCachedOrg()", "file_type": "code", "source_file": "E:\\PROPHUNT CRM\\backend\\middlewares\\auth.js", "source_location": "L19"}, {"id": "middlewares_auth_invalidateorgcache", "label": "invalidateOrgCache()", "file_type": "code", "source_file": "E:\\PROPHUNT CRM\\backend\\middlewares\\auth.js", "source_location": "L23"}, {"id": "middlewares_auth_protect", "label": "protect()", "file_type": "code", "source_file": "E:\\PROPHUNT CRM\\backend\\middlewares\\auth.js", "source_location": "L28"}, {"id": "middlewares_auth_authorize", "label": "authorize()", "file_type": "code", "source_file": "E:\\PROPHUNT CRM\\backend\\middlewares\\auth.js", "source_location": "L81"}], "edges": [{"source": "e_prophunt_crm_backend_middlewares_auth_js", "target": "jsonwebtoken", "relation": "imports_from", "context": "import", "confidence": "EXTRACTED", "source_file": "E:\\PROPHUNT CRM\\backend\\middlewares\\auth.js", "source_location": "L2", "weight": 1.0}, {"source": "e_prophunt_crm_backend_middlewares_auth_js", "target": "middlewares_auth_jwt", "relation": "contains", "confidence": "EXTRACTED", "source_file": "E:\\PROPHUNT CRM\\backend\\middlewares\\auth.js", "source_location": "L2", "weight": 1.0}, {"source": "e_prophunt_crm_backend_middlewares_auth_js", "target": "e_prophunt_crm_backend_models_user_js", "relation": "imports_from", "context": "import", "confidence": "EXTRACTED", "source_file": "E:\\PROPHUNT CRM\\backend\\middlewares\\auth.js", "source_location": "L3", "weight": 1.0}, {"source": "e_prophunt_crm_backend_middlewares_auth_js", "target": "middlewares_auth_user", "relation": "contains", "confidence": "EXTRACTED", "source_file": "E:\\PROPHUNT CRM\\backend\\middlewares\\auth.js", "source_location": "L3", "weight": 1.0}, {"source": "e_prophunt_crm_backend_middlewares_auth_js", "target": "e_prophunt_crm_backend_models_organization_js", "relation": "imports_from", "context": "import", "confidence": "EXTRACTED", "source_file": "E:\\PROPHUNT CRM\\backend\\middlewares\\auth.js", "source_location": "L4", "weight": 1.0}, {"source": "e_prophunt_crm_backend_middlewares_auth_js", "target": "middlewares_auth_organization", "relation": "contains", "confidence": "EXTRACTED", "source_file": "E:\\PROPHUNT CRM\\backend\\middlewares\\auth.js", "source_location": "L4", "weight": 1.0}, {"source": "e_prophunt_crm_backend_middlewares_auth_js", "target": "e_prophunt_crm_backend_middlewares_errorhandler_js", "relation": "imports_from", "context": "import", "confidence": "EXTRACTED", "source_file": "E:\\PROPHUNT CRM\\backend\\middlewares\\auth.js", "source_location": "L5", "weight": 1.0}, {"source": "e_prophunt_crm_backend_middlewares_auth_js", "target": "middlewares_errorhandler_apperror", "relation": "imports", "context": "import", "confidence": "EXTRACTED", "source_file": "E:\\PROPHUNT CRM\\backend\\middlewares\\auth.js", "source_location": "L5", "weight": 1.0}, {"source": "e_prophunt_crm_backend_middlewares_auth_js", "target": "middlewares_auth_apperror", "relation": "contains", "confidence": "EXTRACTED", "source_file": "E:\\PROPHUNT CRM\\backend\\middlewares\\auth.js", "source_location": "L5", "weight": 1.0}, {"source": "e_prophunt_crm_backend_middlewares_auth_js", "target": "middlewares_auth_orgcache", "relation": "contains", "confidence": "EXTRACTED", "source_file": "E:\\PROPHUNT CRM\\backend\\middlewares\\auth.js", "source_location": "L10", "weight": 1.0}, {"source": "e_prophunt_crm_backend_middlewares_auth_js", "target": "middlewares_auth_getcachedorg", "relation": "contains", "confidence": "EXTRACTED", "source_file": "E:\\PROPHUNT CRM\\backend\\middlewares\\auth.js", "source_location": "L13", "weight": 1.0}, {"source": "e_prophunt_crm_backend_middlewares_auth_js", "target": "middlewares_auth_setcachedorg", "relation": "contains", "confidence": "EXTRACTED", "source_file": "E:\\PROPHUNT CRM\\backend\\middlewares\\auth.js", "source_location": "L19", "weight": 1.0}, {"source": "e_prophunt_crm_backend_middlewares_auth_js", "target": "middlewares_auth_invalidateorgcache", "relation": "contains", "confidence": "EXTRACTED", "source_file": "E:\\PROPHUNT CRM\\backend\\middlewares\\auth.js", "source_location": "L23", "weight": 1.0}, {"source": "e_prophunt_crm_backend_middlewares_auth_js", "target": "middlewares_auth_protect", "relation": "contains", "confidence": "EXTRACTED", "source_file": "E:\\PROPHUNT CRM\\backend\\middlewares\\auth.js", "source_location": "L28", "weight": 1.0}, {"source": "e_prophunt_crm_backend_middlewares_auth_js", "target": "middlewares_auth_authorize", "relation": "contains", "confidence": "EXTRACTED", "source_file": "E:\\PROPHUNT CRM\\backend\\middlewares\\auth.js", "source_location": "L81", "weight": 1.0}, {"source": "middlewares_auth_protect", "target": "middlewares_auth_getcachedorg", "relation": "calls", "context": "call", "confidence": "EXTRACTED", "source_file": "E:\\PROPHUNT CRM\\backend\\middlewares\\auth.js", "source_location": "L57", "weight": 1.0}, {"source": "middlewares_auth_protect", "target": "middlewares_auth_setcachedorg", "relation": "calls", "context": "call", "confidence": "EXTRACTED", "source_file": "E:\\PROPHUNT CRM\\backend\\middlewares\\auth.js", "source_location": "L60", "weight": 1.0}], "raw_calls": [{"caller_nid": "middlewares_auth_getcachedorg", "callee": "get", "is_member_call": true, "source_file": "E:\\PROPHUNT CRM\\backend\\middlewares\\auth.js", "source_location": "L14"}, {"caller_nid": "middlewares_auth_getcachedorg", "callee": "String", "is_member_call": false, "source_file": "E:\\PROPHUNT CRM\\backend\\middlewares\\auth.js", "source_location": "L14"}, {"caller_nid": "middlewares_auth_getcachedorg", "callee": "now", "is_member_call": true, "source_file": "E:\\PROPHUNT CRM\\backend\\middlewares\\auth.js", "source_location": "L15"}, {"caller_nid": "middlewares_auth_getcachedorg", "callee": "delete", "is_member_call": true, "source_file": "E:\\PROPHUNT CRM\\backend\\middlewares\\auth.js", "source_location": "L16"}, {"caller_nid": "middlewares_auth_getcachedorg", "callee": "String", "is_member_call": false, "source_file": "E:\\PROPHUNT CRM\\backend\\middlewares\\auth.js", "source_location": "L16"}, {"caller_nid": "middlewares_auth_setcachedorg", "callee": "set", "is_member_call": true, "source_file": "E:\\PROPHUNT CRM\\backend\\middlewares\\auth.js", "source_location": "L20"}, {"caller_nid": "middlewares_auth_setcachedorg", "callee": "String", "is_member_call": false, "source_file": "E:\\PROPHUNT CRM\\backend\\middlewares\\auth.js", "source_location": "L20"}, {"caller_nid": "middlewares_auth_setcachedorg", "callee": "now", "is_member_call": true, "source_file": "E:\\PROPHUNT CRM\\backend\\middlewares\\auth.js", "source_location": "L20"}, {"caller_nid": "middlewares_auth_invalidateorgcache", "callee": "delete", "is_member_call": true, "source_file": "E:\\PROPHUNT CRM\\backend\\middlewares\\auth.js", "source_location": "L24"}, {"caller_nid": "middlewares_auth_invalidateorgcache", "callee": "String", "is_member_call": false, "source_file": "E:\\PROPHUNT CRM\\backend\\middlewares\\auth.js", "source_location": "L24"}, {"caller_nid": "middlewares_auth_protect", "callee": "startsWith", "is_member_call": true, "source_file": "E:\\PROPHUNT CRM\\backend\\middlewares\\auth.js", "source_location": "L36"}, {"caller_nid": "middlewares_auth_protect", "callee": "split", "is_member_call": true, "source_file": "E:\\PROPHUNT CRM\\backend\\middlewares\\auth.js", "source_location": "L37"}, {"caller_nid": "middlewares_auth_protect", "callee": "next", "is_member_call": false, "source_file": "E:\\PROPHUNT CRM\\backend\\middlewares\\auth.js", "source_location": "L41"}, {"caller_nid": "middlewares_auth_protect", "callee": "verify", "is_member_call": true, "source_file": "E:\\PROPHUNT CRM\\backend\\middlewares\\auth.js", "source_location": "L45"}, {"caller_nid": "middlewares_auth_protect", "callee": "select", "is_member_call": true, "source_file": "E:\\PROPHUNT CRM\\backend\\middlewares\\auth.js", "source_location": "L48"}, {"caller_nid": "middlewares_auth_protect", "callee": "findById", "is_member_call": true, "source_file": "E:\\PROPHUNT CRM\\backend\\middlewares\\auth.js", "source_location": "L48"}, {"caller_nid": "middlewares_auth_protect", "callee": "next", "is_member_call": false, "source_file": "E:\\PROPHUNT CRM\\backend\\middlewares\\auth.js", "source_location": "L49"}, {"caller_nid": "middlewares_auth_protect", "callee": "next", "is_member_call": false, "source_file": "E:\\PROPHUNT CRM\\backend\\middlewares\\auth.js", "source_location": "L50"}, {"caller_nid": "middlewares_auth_protect", "callee": "lean", "is_member_call": true, "source_file": "E:\\PROPHUNT CRM\\backend\\middlewares\\auth.js", "source_location": "L59"}, {"caller_nid": "middlewares_auth_protect", "callee": "select", "is_member_call": true, "source_file": "E:\\PROPHUNT CRM\\backend\\middlewares\\auth.js", "source_location": "L59"}, {"caller_nid": "middlewares_auth_protect", "callee": "findById", "is_member_call": true, "source_file": "E:\\PROPHUNT CRM\\backend\\middlewares\\auth.js", "source_location": "L59"}, {"caller_nid": "middlewares_auth_protect", "callee": "next", "is_member_call": false, "source_file": "E:\\PROPHUNT CRM\\backend\\middlewares\\auth.js", "source_location": "L63"}, {"caller_nid": "middlewares_auth_protect", "callee": "next", "is_member_call": false, "source_file": "E:\\PROPHUNT CRM\\backend\\middlewares\\auth.js", "source_location": "L67"}, {"caller_nid": "middlewares_auth_protect", "callee": "next", "is_member_call": false, "source_file": "E:\\PROPHUNT CRM\\backend\\middlewares\\auth.js", "source_location": "L72"}, {"caller_nid": "middlewares_auth_protect", "callee": "next", "is_member_call": false, "source_file": "E:\\PROPHUNT CRM\\backend\\middlewares\\auth.js", "source_location": "L74"}]}